setup.py
django_indb_logger.egg-info/PKG-INFO
django_indb_logger.egg-info/SOURCES.txt
django_indb_logger.egg-info/dependency_links.txt
django_indb_logger.egg-info/not-zip-safe
django_indb_logger.egg-info/requires.txt
django_indb_logger.egg-info/top_level.txt
indb_logger/__init__.py
indb_logger/admin.py
indb_logger/dbh.py
indb_logger/models.py
indb_logger/tests.py