Metadata-Version: 1.0
Name: django-indb-logger
Version: 0.1
Summary: Django app with in-database log handler
Home-page: https://github.com/a1fred/django-indb-logger
Author: a1fred
Author-email: demalf@gmail.com
License: MIT
Platform: any
